terminal_bench/__init__.py
terminal_bench/agents/__init__.py
terminal_bench/agents/agent_factory.py
terminal_bench/agents/agent_name.py
terminal_bench/agents/base_agent.py
terminal_bench/agents/failure_mode.py
terminal_bench/agents/installed_agents/__init__.py
terminal_bench/agents/installed_agents/abstract_installed_agent.py
terminal_bench/agents/installed_agents/aider/__init__.py
terminal_bench/agents/installed_agents/aider/aider-setup.sh
terminal_bench/agents/installed_agents/aider/aider_agent.py
terminal_bench/agents/installed_agents/claude_code/__init__.py
terminal_bench/agents/installed_agents/claude_code/claude-code-setup.sh.j2
terminal_bench/agents/installed_agents/claude_code/claude_code_agent.py
terminal_bench/agents/installed_agents/codex/__init__.py
terminal_bench/agents/installed_agents/codex/codex-setup.sh.j2
terminal_bench/agents/installed_agents/codex/codex_agent.py
terminal_bench/agents/installed_agents/cursor_cli/__init__.py
terminal_bench/agents/installed_agents/cursor_cli/cursor-cli-setup.sh
terminal_bench/agents/installed_agents/cursor_cli/cursor_cli_agent.py
terminal_bench/agents/installed_agents/gemini_cli/__init__.py
terminal_bench/agents/installed_agents/gemini_cli/gemini-cli-setup.sh.j2
terminal_bench/agents/installed_agents/gemini_cli/gemini_cli_agent.py
terminal_bench/agents/installed_agents/goose/__init__.py
terminal_bench/agents/installed_agents/goose/goose-setup.sh
terminal_bench/agents/installed_agents/goose/goose_agent.py
terminal_bench/agents/installed_agents/grok_cli/__init__.py
terminal_bench/agents/installed_agents/grok_cli/grok-cli-setup.sh.j2
terminal_bench/agents/installed_agents/grok_cli/grok_cli_agent.py
terminal_bench/agents/installed_agents/mini_swe_agent/__init__.py
terminal_bench/agents/installed_agents/mini_swe_agent/mini-swe-setup.sh.j2
terminal_bench/agents/installed_agents/mini_swe_agent/mini_swe_agent.py
terminal_bench/agents/installed_agents/opencode/__init__.py
terminal_bench-0.2.17.dist-info/WHEEL
terminal_bench-0.2.17.dist-info/entry_points.txt
terminal_bench-0.2.17.dist-info/METADATA
terminal_bench-0.2.17.dist-info/RECORD
